bmm150/__init__.py
bmm150/bmm150_defs.py
bmm150/main.py
bmm150-0.2.1.dist-info/LICENSE
bmm150-0.2.1.dist-info/WHEEL
bmm150-0.2.1.dist-info/METADATA
bmm150-0.2.1.dist-info/RECORD
