Metadata-Version: 2.1
Name: bmm150
Version: 0.2.1
Summary: A pure python API for the bmm150 magnetic sensor
Home-page: https://gitlab.com/umoreau/bmm150
License: MIT
Author: Ulysse Moreau
Author-email: ulysse.moreau@gmx.fr
Requires-Python: >=3.7,<4.0
Classifier: Development Status :: 4 - Beta
Classifier: Intended Audience :: Developers
Classifier: Intended Audience :: Education
Classifier: License :: OSI Approved :: MIT License
Classifier: Natural Language :: English
Classifier: Programming Language :: Python :: 3
Classifier: Programming Language :: Python :: 3.7
Classifier: Programming Language :: Python :: 3.8
Classifier: Programming Language :: Python :: 3.9
Classifier: Programming Language :: Python :: 3.10
Classifier: Programming Language :: Python :: 3.11
Classifier: Programming Language :: Python :: 3.10
Classifier: Programming Language :: Python :: 3.7
Classifier: Topic :: Software Development :: Embedded Systems
Requires-Dist: enum-tools (>=0.9.0.post1,<0.10.0)
Requires-Dist: smbus2 (>=0.4.2,<0.5.0)
Project-URL: Documentation, https://bmm150.readthedocs.io/
Project-URL: Repository, https://gitlab.com/umoreau/bmm150
